fuzzymatcher/__init__.py
fuzzymatcher/data_getter_abc.py
fuzzymatcher/data_getter_cartesian.py
fuzzymatcher/data_getter_sqlite.py
fuzzymatcher/data_preprocessor_abc.py
fuzzymatcher/data_preprocessor_default.py
fuzzymatcher/matcher.py
fuzzymatcher/record.py
fuzzymatcher/scorer_abc.py
fuzzymatcher/scorer_default.py
fuzzymatcher/tokencomparison.py
fuzzymatcher/utils.py
fuzzymatcher-0.0.6.dist-info/LICENSE
fuzzymatcher-0.0.6.dist-info/METADATA
fuzzymatcher-0.0.6.dist-info/WHEEL
fuzzymatcher-0.0.6.dist-info/top_level.txt
fuzzymatcher-0.0.6.dist-info/RECORD
